{
	"time": 1700392201965,
	"iot_code": "ems0000000",
	"runState": 1,
	"Error": 0,
	"AuxiliaryKWH":["0.000","0.000","0.000","0.000","0.000"],
	"E2PKWH":["0.000","0.000","0.000","0.000","0.000"],
	"E2OKWH":["0.000","0.000","0.000","0.000","0.000"],
	"Profit": "0.000",
	"GridKVA": "0.000",
	"PUMdemand": "0.000",
	"WorkKVA": "0.000",
	"PCSScheduleKVA": "0.000",
	"PCSKVA": "0.000",
	"AuxiliaryKVA": "0.000",
	"BMSSOC": "0.000",
	"BMSSOH": "0.000",
	"BMSKVA": "0.000",
	"O_sigma": "0.000",
	"BalaRun": 0,
	"Cell_Diff": "0.000"
}
